pupil_labs/dynamic_content_on_rim/__init__.py
pupil_labs/dynamic_content_on_rim/dynamic_rim.py
pupil_labs/dynamic_content_on_rim/parser.py
pupil_labs/dynamic_content_on_rim/recording/recording.py
pupil_labs/dynamic_content_on_rim/uitools/__init__.py
pupil_labs/dynamic_content_on_rim/uitools/get_corners.py
pupil_labs/dynamic_content_on_rim/uitools/ui_tools.py
pupil_labs/dynamic_content_on_rim/video/__init__.py
pupil_labs/dynamic_content_on_rim/video/read.py
pupil_labs_dynamic_rim-1.0.4.dist-info/LICENSE
pupil_labs_dynamic_rim-1.0.4.dist-info/METADATA
pupil_labs_dynamic_rim-1.0.4.dist-info/WHEEL
pupil_labs_dynamic_rim-1.0.4.dist-info/entry_points.txt
pupil_labs_dynamic_rim-1.0.4.dist-info/top_level.txt
pupil_labs_dynamic_rim-1.0.4.dist-info/RECORD
